example_shared_isort_profile.py
example_shared_isort_profile-0.1.0.dist-info/WHEEL
example_shared_isort_profile-0.1.0.dist-info/METADATA
example_shared_isort_profile-0.1.0.dist-info/entry_points.txt
example_shared_isort_profile-0.1.0.dist-info/RECORD
